Metadata-Version: 1.1
Name: checkidcreator
Version: 0.0.3
Summary: A program to generate a random id of any length greater than 1 with a check digit.
Home-page: UNKNOWN
Author: Pratham Aggarwal
Author-email: me@prathamaggarwal.com
License: MIT
Keywords: id generator,check id,id creator
Platform: UNKNOWN
Classifier: Development Status :: 4 - Beta
Classifier: Intended Audience :: Education
Classifier: License :: OSI Approved :: MIT License
Classifier: Programming Language :: Python :: 3
